musx/__init__.py
musx/csound.py
musx/envs.py
musx/frac.py
musx/gens.py
musx/interval.py
musx/note.py
musx/paint.py
musx/patterns.py
musx/pc.py
musx/pitch.py
musx/ran.py
musx/rhythm.py
musx/score.py
musx/seq.py
musx/spectral.py
musx/tools.py
musx/midi/__init__.py
musx/midi/gm.py
musx/midi/midievent.py
musx/midi/midifile.py
musx/midi/midimsg.py
musx/mxml/__init__.py
musx/mxml/barline.py
musx/mxml/clef.py
musx/mxml/key.py
musx/mxml/mark.py
musx/mxml/measure.py
musx/mxml/meter.py
musx/mxml/mode.py
musx/mxml/musicxml.py
musx/mxml/notation.py
musx/mxml/part.py
musx/mxml/voice.py
musx-3.0.0.dist-info/LICENSE.md
musx-3.0.0.dist-info/METADATA
musx-3.0.0.dist-info/WHEEL
musx-3.0.0.dist-info/top_level.txt
musx-3.0.0.dist-info/RECORD
