Metadata-Version: 2.1
Name: musx
Version: 3.0.0
Summary: An algorithmic music composition package based in part on the author's Common Music and Grace systems.
Home-page: https://github.com/musx-admin/musx
Author: Rick Taube
Author-email: taube@illinois.edu
Classifier: Programming Language :: Python :: 3
Classifier: License :: OSI Approved :: BSD License
Classifier: Operating System :: OS Independent
Requires-Python: >=3.9
License-File: LICENSE.md
